{"data": [["July 2021-December 2022","ind","July 2021-December 2022","indA",0,"Sleep","Demographic characteristics",null,"","63.8","51.6, 74.8","50.4","37.6, 63.1","71.6","67.7, 75.2","79.2","67.7, 88.0",""]], "classes": ["Year","row_var","rowLevels","rowLevNum","selected","stat_group","col_group","new_caption2","new_caption","Asian__raceA__BEDTIME__coef","Asian__raceA__BEDTIME__se","Black__raceB__BEDTIME__coef","Black__raceB__BEDTIME__se","White__raceC__BEDTIME__coef","White__raceC__BEDTIME__se","All other races__raceD__BEDTIME__coef","All other races__raceD__BEDTIME__se","subLevels"], "names": ["Year","row_var","rowLevels","rowLevNum","selected","stat_group","col_group","new_caption2","new_caption","Asian","Asian","Black","Black","White","White","All other races","All other races","subLevels"], "caption": ["Percentage of teens aged 12-17 years who have a regular bedtime most days or every day, United States, July 2021—December 2022"], "caption2": [""], "caption3": [null]}
