{"data": [["July 2021-December 2022","ind","July 2021-December 2022","indA",0,"Bullying","Demographic characteristics","","Based on the question, \"During the past 12 months, how often were you bullied, picked on, or excluded by other youth?\"","16.9","9.9, 26.2","25.4","15.7, 37.3","36.8","32.6, 41.2","39.8","26.6, 54.2",""],["July 2021-December 2023","ind","July 2021-December 2023","indA",0,"Bullying","Demographic characteristics","","Based on the question, \"During the past 12 months, how often were you bullied, picked on, or excluded by other youth?\"","16.2","10.5,23.5","23.7","16.1,32.8","37.7","34.6,40.8","46.5","35.7,57.5",""]], "classes": ["Year","row_var","rowLevels","rowLevNum","selected","stat_group","col_group","new_caption","new_caption2","Asian__raceA__EVER_BULLIED__coef","Asian__raceA__EVER_BULLIED__se","Black__raceB__EVER_BULLIED__coef","Black__raceB__EVER_BULLIED__se","White__raceC__EVER_BULLIED__coef","White__raceC__EVER_BULLIED__se","All other races__raceD__EVER_BULLIED__coef","All other races__raceD__EVER_BULLIED__se","subLevels"], "names": ["Year","row_var","rowLevels","rowLevNum","selected","stat_group","col_group","new_caption","new_caption2","Asian","Asian","Black","Black","White","White","All other races","All other races","subLevels"], "caption": ["Percentage of teens aged 12-17 years who were ever bullied in the past 12 months, United States, July 2021—December 2022","Percentage of teens aged 12-17 years who were ever bullied in the past 12 months, United States, July 2021—December 2023"], "caption2": [""], "caption3": ["Based on the question, \"During the past 12 months, how often were you bullied, picked on, or excluded by other youth?\""]}
