{"data": [["July 2021-December 2022","ind","July 2021-December 2022","indA",0,"Mental health care and unmet n","Demographic characteristics",null,"","17.1","11.1, 24.6","12.4","6.7, 20.3","12.2","8.6, 16.8","13.9","9.5, 19.3",""]], "classes": ["Year","row_var","rowLevels","rowLevNum","selected","stat_group","col_group","new_caption2","new_caption","Midwest__regionA__MH_MEDS__coef","Midwest__regionA__MH_MEDS__se","Northeast__regionB__MH_MEDS__coef","Northeast__regionB__MH_MEDS__se","South__regionC__MH_MEDS__coef","South__regionC__MH_MEDS__se","West__regionD__MH_MEDS__coef","West__regionD__MH_MEDS__se","subLevels"], "names": ["Year","row_var","rowLevels","rowLevNum","selected","stat_group","col_group","new_caption2","new_caption","Midwest","Midwest","Northeast","Northeast","South","South","West","West","subLevels"], "caption": ["Percentage of teens aged 12-17 years who took prescription medication to help with emotions, concentration, behavior or mental health in the past 12 months, United States, July 2021—December 2022"], "caption2": [""], "caption3": [null]}
