{"data": [["July 2021-December 2022","ind","July 2021-December 2022","indA",0,"Social and emotional supports","Demographic characteristics",null,"","55.2","48.4, 61.8","60.8","56.7, 64.8",""]], "classes": ["Year","row_var","rowLevels","rowLevNum","selected","stat_group","col_group","new_caption2","new_caption","Single parent__parnumA__SOEMSUPP__coef","Single parent__parnumA__SOEMSUPP__se","Two parents__parnumB__SOEMSUPP__coef","Two parents__parnumB__SOEMSUPP__se","subLevels"], "names": ["Year","row_var","rowLevels","rowLevNum","selected","stat_group","col_group","new_caption2","new_caption","Single parent","Single parent","Two parents","Two parents","subLevels"], "caption": ["Percentage of teens aged 12-17 years who always or usually received social and emotional support in the past 12 months, United States, July 2021—December 2022"], "caption2": [""], "caption3": [null]}
